utils_jinja_sqlite/__init__.py
utils_jinja_sqlite/bind.py
utils_jinja_sqlite/connect.py
utils_jinja_sqlite/format.py
utils_jinja_sqlite-0.0.6.dist-info/WHEEL
utils_jinja_sqlite-0.0.6.dist-info/METADATA
utils_jinja_sqlite-0.0.6.dist-info/RECORD
