Metadata-Version: 2.1
Name: utils-jinja-sqlite
Version: 0.0.6
Summary: Common helper utility functions used when connecting to sqlite databases and binding SQL values from python variables.
Author: Marcelino G. Veloso III
Author-email: mars@veloso.one
Requires-Python: >=3.10,<4.0
Classifier: Programming Language :: Python :: 3
Classifier: Programming Language :: Python :: 3.10
Requires-Dist: Jinja2 (>=3.1.2,<4.0.0)
Requires-Dist: aiosqlite (>=0.17.0,<0.18.0)
Requires-Dist: python-dotenv (>=0.19,<0.20)
Requires-Dist: rich (>=12.2,<13.0)
Requires-Dist: sqlparse (>=0.4.2,<0.5.0)
